piinspy/__init__.py
piinspy/ins.json
piinspy/ins_class.py
piinspy/ins_function.py
piinspy/insconst.py
piinspy/log.py
piinspy/package.json
inspy-0.2.1.dist-info/LICENSE
inspy-0.2.1.dist-info/METADATA
inspy-0.2.1.dist-info/WHEEL
inspy-0.2.1.dist-info/top_level.txt
inspy-0.2.1.dist-info/RECORD
