Metadata-Version: 2.1
Name: inspy
Version: 0.2.1
Summary: scan and control for instrument that support SCPI COMMAND added 34461A
Home-page: https://github.com/AceWalTer/inspy
Author: Yafei Wang
Author-email: yafei.wang@pisemi.com
Classifier: Development Status :: 3 - Alpha
Classifier: Intended Audience :: Developers
Classifier: License :: OSI Approved :: MIT License
Classifier: Programming Language :: Python :: 3
Classifier: Programming Language :: Python :: 3.7
Requires-Python: >=3.6
License-File: LICENSE
Requires-Dist: pyvisa >=1.12.0
Requires-Dist: colorama ~=0.4.6
Requires-Dist: setuptools ~=68.0.0
